{
    "pagination": {
        "last_visible_page": 1207,
        "has_next_page": true,
        "current_page": 717,
        "items": {
            "count": 25,
            "total": 30159,
            "per_page": 25
        }
    },
    "data": [
        {
            "mal_id": 44140,
            "url": "https://myanimelist.net/anime/44140/Xiong_Chumo__Xiongxiong_Huanle_Song",
            "images": {
                "jpg": {
                    "image_url": "https://myanimelist.net/images/anime/1650/122986.jpg",
                    "small_image_url": "https://myanimelist.net/images/anime/1650/122986t.jpg",
                    "large_image_url": "https://myanimelist.net/images/anime/1650/122986l.jpg"
                },
                "webp": {
                    "image_url": "https://myanimelist.net/images/anime/1650/122986.webp",
                    "small_image_url": "https://myanimelist.net/images/anime/1650/122986t.webp",
                    "large_image_url": "https://myanimelist.net/images/anime/1650/122986l.webp"
                }
            },
            "trailer": {
                "youtube_id": null,
                "url": null,
                "embed_url": null,
                "images": {
                    "image_url": null,
                    "small_image_url": null,
                    "medium_image_url": null,
                    "large_image_url": null,
                    "maximum_image_url": null
                }
            },
            "approved": true,
            "titles": [
                {
                    "type": "Default",
                    "title": "Xiong Chumo: Xiongxiong Huanle Song"
                },
                {
                    "type": "Japanese",
                    "title": "\u718a\u51fa\u6ca1\u4e4b\u718a\u718a\u6b22\u4e50\u9882"
                },
                {
                    "type": "English",
                    "title": "Boonie Cub Tune Club"
                }
            ],
            "title": "Xiong Chumo: Xiongxiong Huanle Song",
            "title_english": "Boonie Cub Tune Club",
            "title_japanese": "\u718a\u51fa\u6ca1\u4e4b\u718a\u718a\u6b22\u4e50\u9882",
            "title_synonyms": [],
            "type": "TV",
            "source": "Original",
            "episodes": 13,
            "status": "Finished Airing",
            "airing": false,
            "aired": {
                "from": "2019-08-10T00:00:00+00:00",
                "to": null,
                "prop": {
                    "from": {
                        "day": 10,
                        "month": 8,
                        "year": 2019
                    },
                    "to": {
                        "day": null,
                        "month": null,
                        "year": null
                    }
                },
                "string": "Aug 10, 2019 to ?"
            },
            "duration": "3 min per ep",
            "rating": "PG - Children",
            "score": null,
            "scored_by": null,
            "rank": 22036,
            "popularity": 25239,
            "members": 147,
            "favorites": 0,
            "synopsis": null,
            "background": "",
            "season": null,
            "year": null,
            "broadcast": {
                "day": null,
                "time": null,
                "timezone": null,
                "string": "Unknown"
            },
            "producers": [],
            "licensors": [],
            "studios": [
                {
                    "mal_id": 2611,
                    "type": "anime",
                    "name": "Fantawild Animation",
                    "url": "https://myanimelist.net/anime/producer/2611/Fantawild_Animation"
                }
            ],
            "genres": [],
            "explicit_genres": [],
            "themes": [
                {
                    "mal_id": 19,
                    "type": "anime",
                    "name": "Music",
                    "url": "https://myanimelist.net/anime/genre/19/Music"
                }
            ],
            "demographics": [
                {
                    "mal_id": 15,
                    "type": "anime",
                    "name": "Kids",
                    "url": "https://myanimelist.net/anime/genre/15/Kids"
                }
            ]
        },
        {
            "mal_id": 44141,
            "url": "https://myanimelist.net/anime/44141/Watashi_ni_Tenshi_ga_Maiorita_Precious_Friends",
            "images": {
                "jpg": {
                    "image_url": "https://myanimelist.net/images/anime/1267/124382.jpg",
                    "small_image_url": "https://myanimelist.net/images/anime/1267/124382t.jpg",
                    "large_image_url": "https://myanimelist.net/images/anime/1267/124382l.jpg"
                },
                "webp": {
                    "image_url": "https://myanimelist.net/images/anime/1267/124382.webp",
                    "small_image_url": "https://myanimelist.net/images/anime/1267/124382t.webp",
                    "large_image_url": "https://myanimelist.net/images/anime/1267/124382l.webp"
                }
            },
            "trailer": {
                "youtube_id": null,
                "url": null,
                "embed_url": "https://www.youtube-nocookie.com/embed/40SI4hlkFts?enablejsapi=1&wmode=opaque&autoplay=1",
                "images": {
                    "image_url": null,
                    "small_image_url": null,
                    "medium_image_url": null,
                    "large_image_url": null,
                    "maximum_image_url": null
                }
            },
            "approved": true,
            "titles": [
                {
                    "type": "Default",
                    "title": "Watashi ni Tenshi ga Maiorita! Precious Friends"
                },
                {
                    "type": "Synonym",
                    "title": "Wataten! An Angel Flew Down to Me"
                },
                {
                    "type": "Japanese",
                    "title": "\u79c1\u306b\u5929\u4f7f\u304c\u821e\u3044\u964d\u308a\u305f! \u30d7\u30ec\u30b7\u30e3\u30b9\u30fb\u30d5\u30ec\u30f3\u30ba"
                },
                {
                    "type": "English",
                    "title": "Wataten! An Angel Flew Down to Me: Precious Friends"
                }
            ],
            "title": "Watashi ni Tenshi ga Maiorita! Precious Friends",
            "title_english": "Wataten! An Angel Flew Down to Me: Precious Friends",
            "title_japanese": "\u79c1\u306b\u5929\u4f7f\u304c\u821e\u3044\u964d\u308a\u305f! \u30d7\u30ec\u30b7\u30e3\u30b9\u30fb\u30d5\u30ec\u30f3\u30ba",
            "title_synonyms": [
                "Wataten! An Angel Flew Down to Me"
            ],
            "type": "Movie",
            "source": "4-koma manga",
            "episodes": 1,
            "status": "Finished Airing",
            "airing": false,
            "aired": {
                "from": "2022-10-14T00:00:00+00:00",
                "to": null,
                "prop": {
                    "from": {
                        "day": 14,
                        "month": 10,
                        "year": 2022
                    },
                    "to": {
                        "day": null,
                        "month": null,
                        "year": null
                    }
                },
                "string": "Oct 14, 2022"
            },
            "duration": "1 hr 6 min",
            "rating": "PG-13 - Teens 13 or older",
            "score": 7.59,
            "scored_by": 8230,
            "rank": 1877,
            "popularity": 4953,
            "members": 26337,
            "favorites": 75,
            "synopsis": "Hana, Hinata, Noa, Koyori, and Kanon are always good friends. Today, they are having a friendly sweets party at home with Miyako's homemade sweets! The flower-shaped cookies look just like the hair ornaments worn by Hana. The hair ornament was a precious treasure that Hana received from her grandmother when she was little, and everyone was intrigued by the story. And as \"practice for the school trip,\" they decide to go visit Hana's grandmother's house...! The \"first\" outing for everyone is about to begin.\n\n(Source: Crunchyroll News)",
            "background": "",
            "season": null,
            "year": null,
            "broadcast": {
                "day": null,
                "time": null,
                "timezone": null,
                "string": null
            },
            "producers": [
                {
                    "mal_id": 238,
                    "type": "anime",
                    "name": "AT-X",
                    "url": "https://myanimelist.net/anime/producer/238/AT-X"
                },
                {
                    "mal_id": 464,
                    "type": "anime",
                    "name": "flying DOG",
                    "url": "https://myanimelist.net/anime/producer/464/flying_DOG"
                },
                {
                    "mal_id": 1551,
                    "type": "anime",
                    "name": "Kadokawa Media House",
                    "url": "https://myanimelist.net/anime/producer/1551/Kadokawa_Media_House"
                },
                {
                    "mal_id": 1582,
                    "type": "anime",
                    "name": "Ichijinsha",
                    "url": "https://myanimelist.net/anime/producer/1582/Ichijinsha"
                },
                {
                    "mal_id": 1696,
                    "type": "anime",
                    "name": "Kadokawa",
                    "url": "https://myanimelist.net/anime/producer/1696/Kadokawa"
                },
                {
                    "mal_id": 1916,
                    "type": "anime",
                    "name": "Kadokawa Animation",
                    "url": "https://myanimelist.net/anime/producer/1916/Kadokawa_Animation"
                },
                {
                    "mal_id": 2106,
                    "type": "anime",
                    "name": "Sony Music Solutions",
                    "url": "https://myanimelist.net/anime/producer/2106/Sony_Music_Solutions"
                }
            ],
            "licensors": [],
            "studios": [
                {
                    "mal_id": 95,
                    "type": "anime",
                    "name": "Doga Kobo",
                    "url": "https://myanimelist.net/anime/producer/95/Doga_Kobo"
                }
            ],
            "genres": [
                {
                    "mal_id": 4,
                    "type": "anime",
                    "name": "Comedy",
                    "url": "https://myanimelist.net/anime/genre/4/Comedy"
                }
            ],
            "explicit_genres": [],
            "themes": [
                {
                    "mal_id": 52,
                    "type": "anime",
                    "name": "CGDCT",
                    "url": "https://myanimelist.net/anime/genre/52/CGDCT"
                }
            ],
            "demographics": []
        },
        {
            "mal_id": 44144,
            "url": "https://myanimelist.net/anime/44144/Sai_Er_Hao_Season_2__Sheng_Zhe_Ni_Xi",
            "images": {
                "jpg": {
                    "image_url": "https://myanimelist.net/images/anime/1340/117993.jpg",
                    "small_image_url": "https://myanimelist.net/images/anime/1340/117993t.jpg",
                    "large_image_url": "https://myanimelist.net/images/anime/1340/117993l.jpg"
                },
                "webp": {
                    "image_url": "https://myanimelist.net/images/anime/1340/117993.webp",
                    "small_image_url": "https://myanimelist.net/images/anime/1340/117993t.webp",
                    "large_image_url": "https://myanimelist.net/images/anime/1340/117993l.webp"
                }
            },
            "trailer": {
                "youtube_id": null,
                "url": null,
                "embed_url": null,
                "images": {
                    "image_url": null,
                    "small_image_url": null,
                    "medium_image_url": null,
                    "large_image_url": null,
                    "maximum_image_url": null
                }
            },
            "approved": true,
            "titles": [
                {
                    "type": "Default",
                    "title": "Sai Er Hao Season 2: Sheng Zhe Ni Xi"
                },
                {
                    "type": "Synonym",
                    "title": "Seer Second Season"
                },
                {
                    "type": "Japanese",
                    "title": "\u8d5b\u5c14\u53f7\u4e4b\u5723\u8005\u9006\u88ad"
                }
            ],
            "title": "Sai Er Hao Season 2: Sheng Zhe Ni Xi",
            "title_english": null,
            "title_japanese": "\u8d5b\u5c14\u53f7\u4e4b\u5723\u8005\u9006\u88ad",
            "title_synonyms": [
                "Seer Second Season"
            ],
            "type": "TV",
            "source": "Original",
            "episodes": 40,
            "status": "Finished Airing",
            "airing": false,
            "aired": {
                "from": "2013-02-01T00:00:00+00:00",
                "to": "2013-03-16T00:00:00+00:00",
                "prop": {
                    "from": {
                        "day": 1,
                        "month": 2,
                        "year": 2013
                    },
                    "to": {
                        "day": 16,
                        "month": 3,
                        "year": 2013
                    }
                },
                "string": "Feb 1, 2013 to Mar 16, 2013"
            },
            "duration": "13 min per ep",
            "rating": "PG - Children",
            "score": null,
            "scored_by": null,
            "rank": 19990,
            "popularity": 22949,
            "members": 222,
            "favorites": 0,
            "synopsis": null,
            "background": "",
            "season": "winter",
            "year": 2013,
            "broadcast": {
                "day": null,
                "time": null,
                "timezone": null,
                "string": "Unknown"
            },
            "producers": [],
            "licensors": [],
            "studios": [],
            "genres": [],
            "explicit_genres": [],
            "themes": [],
            "demographics": [
                {
                    "mal_id": 15,
                    "type": "anime",
                    "name": "Kids",
                    "url": "https://myanimelist.net/anime/genre/15/Kids"
                }
            ]
        },
        {
            "mal_id": 44145,
            "url": "https://myanimelist.net/anime/44145/Sai_Er_Hao_Season_3__Guangming_De_Jiushu",
            "images": {
                "jpg": {
                    "image_url": "https://myanimelist.net/images/anime/1883/117994.jpg",
                    "small_image_url": "https://myanimelist.net/images/anime/1883/117994t.jpg",
                    "large_image_url": "https://myanimelist.net/images/anime/1883/117994l.jpg"
                },
                "webp": {
                    "image_url": "https://myanimelist.net/images/anime/1883/117994.webp",
                    "small_image_url": "https://myanimelist.net/images/anime/1883/117994t.webp",
                    "large_image_url": "https://myanimelist.net/images/anime/1883/117994l.webp"
                }
            },
            "trailer": {
                "youtube_id": null,
                "url": null,
                "embed_url": null,
                "images": {
                    "image_url": null,
                    "small_image_url": null,
                    "medium_image_url": null,
                    "large_image_url": null,
                    "maximum_image_url": null
                }
            },
            "approved": true,
            "titles": [
                {
                    "type": "Default",
                    "title": "Sai Er Hao Season 3: Guangming De Jiushu"
                },
                {
                    "type": "Synonym",
                    "title": "Seer Third Season"
                },
                {
                    "type": "Japanese",
                    "title": "\u8d5b\u5c14\u53f7\u7b2c3\u5b63\uff1a\u5149\u660e\u7684\u6551\u8d4e"
                }
            ],
            "title": "Sai Er Hao Season 3: Guangming De Jiushu",
            "title_english": null,
            "title_japanese": "\u8d5b\u5c14\u53f7\u7b2c3\u5b63\uff1a\u5149\u660e\u7684\u6551\u8d4e",
            "title_synonyms": [
                "Seer Third Season"
            ],
            "type": "TV",
            "source": "Game",
            "episodes": 30,
            "status": "Finished Airing",
            "airing": false,
            "aired": {
                "from": "2014-05-16T00:00:00+00:00",
                "to": "2014-01-01T00:00:00+00:00",
                "prop": {
                    "from": {
                        "day": 16,
                        "month": 5,
                        "year": 2014
                    },
                    "to": {
                        "day": 1,
                        "month": 1,
                        "year": 2014
                    }
                },
                "string": "May 16, 2014 to 2014"
            },
            "duration": "13 min per ep",
            "rating": "PG - Children",
            "score": null,
            "scored_by": null,
            "rank": 19991,
            "popularity": 24779,
            "members": 158,
            "favorites": 0,
            "synopsis": null,
            "background": "",
            "season": null,
            "year": null,
            "broadcast": {
                "day": null,
                "time": null,
                "timezone": null,
                "string": "Unknown"
            },
            "producers": [],
            "licensors": [],
            "studios": [],
            "genres": [],
            "explicit_genres": [],
            "themes": [],
            "demographics": [
                {
                    "mal_id": 15,
                    "type": "anime",
                    "name": "Kids",
                    "url": "https://myanimelist.net/anime/genre/15/Kids"
                }
            ]
        },
        {
            "mal_id": 44146,
            "url": "https://myanimelist.net/anime/44146/Sai_Er_Hao_Season_4__Zhanshen_Fengyun_Jue",
            "images": {
                "jpg": {
                    "image_url": "https://myanimelist.net/images/anime/1749/117995.jpg",
                    "small_image_url": "https://myanimelist.net/images/anime/1749/117995t.jpg",
                    "large_image_url": "https://myanimelist.net/images/anime/1749/117995l.jpg"
                },
                "webp": {
                    "image_url": "https://myanimelist.net/images/anime/1749/117995.webp",
                    "small_image_url": "https://myanimelist.net/images/anime/1749/117995t.webp",
                    "large_image_url": "https://myanimelist.net/images/anime/1749/117995l.webp"
                }
            },
            "trailer": {
                "youtube_id": null,
                "url": null,
                "embed_url": null,
                "images": {
                    "image_url": null,
                    "small_image_url": null,
                    "medium_image_url": null,
                    "large_image_url": null,
                    "maximum_image_url": null
                }
            },
            "approved": true,
            "titles": [
                {
                    "type": "Default",
                    "title": "Sai Er Hao Season 4: Zhanshen Fengyun Jue"
                },
                {
                    "type": "Synonym",
                    "title": "Seer Fourth Season"
                },
                {
                    "type": "Japanese",
                    "title": "\u8d5b\u5c14\u53f7\u7b2c4\u5b63\uff1a\u6218\u795e\u98ce\u4e91\u51b3"
                }
            ],
            "title": "Sai Er Hao Season 4: Zhanshen Fengyun Jue",
            "title_english": null,
            "title_japanese": "\u8d5b\u5c14\u53f7\u7b2c4\u5b63\uff1a\u6218\u795e\u98ce\u4e91\u51b3",
            "title_synonyms": [
                "Seer Fourth Season"
            ],
            "type": "TV",
            "source": "Game",
            "episodes": 30,
            "status": "Finished Airing",
            "airing": false,
            "aired": {
                "from": "2015-01-16T00:00:00+00:00",
                "to": "2015-03-06T00:00:00+00:00",
                "prop": {
                    "from": {
                        "day": 16,
                        "month": 1,
                        "year": 2015
                    },
                    "to": {
                        "day": 6,
                        "month": 3,
                        "year": 2015
                    }
                },
                "string": "Jan 16, 2015 to Mar 6, 2015"
            },
            "duration": "13 min per ep",
            "rating": "PG - Children",
            "score": null,
            "scored_by": null,
            "rank": 19992,
            "popularity": 23015,
            "members": 219,
            "favorites": 0,
            "synopsis": null,
            "background": "",
            "season": "winter",
            "year": 2015,
            "broadcast": {
                "day": null,
                "time": null,
                "timezone": null,
                "string": "Unknown"
            },
            "producers": [],
            "licensors": [],
            "studios": [],
            "genres": [],
            "explicit_genres": [],
            "themes": [],
            "demographics": [
                {
                    "mal_id": 15,
                    "type": "anime",
                    "name": "Kids",
                    "url": "https://myanimelist.net/anime/genre/15/Kids"
                }
            ]
        },
        {
            "mal_id": 44147,
            "url": "https://myanimelist.net/anime/44147/Sai_Er_Hao_Season_5__Lie_Tian_Kun_Shou",
            "images": {
                "jpg": {
                    "image_url": "https://myanimelist.net/images/anime/1817/117997.jpg",
                    "small_image_url": "https://myanimelist.net/images/anime/1817/117997t.jpg",
                    "large_image_url": "https://myanimelist.net/images/anime/1817/117997l.jpg"
                },
                "webp": {
                    "image_url": "https://myanimelist.net/images/anime/1817/117997.webp",
                    "small_image_url": "https://myanimelist.net/images/anime/1817/117997t.webp",
                    "large_image_url": "https://myanimelist.net/images/anime/1817/117997l.webp"
                }
            },
            "trailer": {
                "youtube_id": null,
                "url": null,
                "embed_url": null,
                "images": {
                    "image_url": null,
                    "small_image_url": null,
                    "medium_image_url": null,
                    "large_image_url": null,
                    "maximum_image_url": null
                }
            },
            "approved": true,
            "titles": [
                {
                    "type": "Default",
                    "title": "Sai Er Hao Season 5: Lie Tian Kun Shou"
                },
                {
                    "type": "Synonym",
                    "title": "Seer Fifth Season"
                },
                {
                    "type": "Japanese",
                    "title": "\u8d5b\u5c14\u53f7\u7b2c5\u5b63\uff1a\u730e\u5929\u56f0\u517d"
                }
            ],
            "title": "Sai Er Hao Season 5: Lie Tian Kun Shou",
            "title_english": null,
            "title_japanese": "\u8d5b\u5c14\u53f7\u7b2c5\u5b63\uff1a\u730e\u5929\u56f0\u517d",
            "title_synonyms": [
                "Seer Fifth Season"
            ],
            "type": "TV",
            "source": "Game",
            "episodes": 30,
            "status": "Finished Airing",
            "airing": false,
            "aired": {
                "from": "2015-04-01T00:00:00+00:00",
                "to": "2015-07-23T00:00:00+00:00",
                "prop": {
                    "from": {
                        "day": 1,
                        "month": 4,
                        "year": 2015
                    },
                    "to": {
                        "day": 23,
                        "month": 7,
                        "year": 2015
                    }
                },
                "string": "Apr 1, 2015 to Jul 23, 2015"
            },
            "duration": "13 min per ep",
            "rating": "PG - Children",
            "score": null,
            "scored_by": null,
            "rank": 19993,
            "popularity": 23779,
            "members": 190,
            "favorites": 0,
            "synopsis": null,
            "background": "",
            "season": "spring",
            "year": 2015,
            "broadcast": {
                "day": null,
                "time": null,
                "timezone": null,
                "string": "Unknown"
            },
            "producers": [],
            "licensors": [],
            "studios": [],
            "genres": [],
            "explicit_genres": [],
            "themes": [],
            "demographics": [
                {
                    "mal_id": 15,
                    "type": "anime",
                    "name": "Kids",
                    "url": "https://myanimelist.net/anime/genre/15/Kids"
                }
            ]
        },
        {
            "mal_id": 44148,
            "url": "https://myanimelist.net/anime/44148/Sai_Er_Hao_Season_6__Cangqiong_Liehuo",
            "images": {
                "jpg": {
                    "image_url": "https://myanimelist.net/images/anime/1446/117998.jpg",
                    "small_image_url": "https://myanimelist.net/images/anime/1446/117998t.jpg",
                    "large_image_url": "https://myanimelist.net/images/anime/1446/117998l.jpg"
                },
                "webp": {
                    "image_url": "https://myanimelist.net/images/anime/1446/117998.webp",
                    "small_image_url": "https://myanimelist.net/images/anime/1446/117998t.webp",
                    "large_image_url": "https://myanimelist.net/images/anime/1446/117998l.webp"
                }
            },
            "trailer": {
                "youtube_id": null,
                "url": null,
                "embed_url": null,
                "images": {
                    "image_url": null,
                    "small_image_url": null,
                    "medium_image_url": null,
                    "large_image_url": null,
                    "maximum_image_url": null
                }
            },
            "approved": true,
            "titles": [
                {
                    "type": "Default",
                    "title": "Sai Er Hao Season 6: Cangqiong Liehuo"
                },
                {
                    "type": "Synonym",
                    "title": "Seer Sixth Season"
                },
                {
                    "type": "Japanese",
                    "title": "\u8d5b\u5c14\u53f7\u7b2c6\u5b63\uff1a\u82cd\u7a79\u70c8\u706b"
                }
            ],
            "title": "Sai Er Hao Season 6: Cangqiong Liehuo",
            "title_english": null,
            "title_japanese": "\u8d5b\u5c14\u53f7\u7b2c6\u5b63\uff1a\u82cd\u7a79\u70c8\u706b",
            "title_synonyms": [
                "Seer Sixth Season"
            ],
            "type": "TV",
            "source": "Game",
            "episodes": 30,
            "status": "Finished Airing",
            "airing": false,
            "aired": {
                "from": "2016-01-01T00:00:00+00:00",
                "to": "2016-04-09T00:00:00+00:00",
                "prop": {
                    "from": {
                        "day": 1,
                        "month": 1,
                        "year": 2016
                    },
                    "to": {
                        "day": 9,
                        "month": 4,
                        "year": 2016
                    }
                },
                "string": "Jan 1, 2016 to Apr 9, 2016"
            },
            "duration": "15 min per ep",
            "rating": "PG - Children",
            "score": null,
            "scored_by": null,
            "rank": 19994,
            "popularity": 23362,
            "members": 204,
            "favorites": 0,
            "synopsis": null,
            "background": "",
            "season": "winter",
            "year": 2016,
            "broadcast": {
                "day": null,
                "time": null,
                "timezone": null,
                "string": "Unknown"
            },
            "producers": [],
            "licensors": [],
            "studios": [],
            "genres": [],
            "explicit_genres": [],
            "themes": [],
            "demographics": [
                {
                    "mal_id": 15,
                    "type": "anime",
                    "name": "Kids",
                    "url": "https://myanimelist.net/anime/genre/15/Kids"
                }
            ]
        },
        {
            "mal_id": 44149,
            "url": "https://myanimelist.net/anime/44149/Sai_Er_Hao_Season_7__Yuzhou_Zhi_Yan",
            "images": {
                "jpg": {
                    "image_url": "https://myanimelist.net/images/anime/1724/117999.jpg",
                    "small_image_url": "https://myanimelist.net/images/anime/1724/117999t.jpg",
                    "large_image_url": "https://myanimelist.net/images/anime/1724/117999l.jpg"
                },
                "webp": {
                    "image_url": "https://myanimelist.net/images/anime/1724/117999.webp",
                    "small_image_url": "https://myanimelist.net/images/anime/1724/117999t.webp",
                    "large_image_url": "https://myanimelist.net/images/anime/1724/117999l.webp"
                }
            },
            "trailer": {
                "youtube_id": null,
                "url": null,
                "embed_url": null,
                "images": {
                    "image_url": null,
                    "small_image_url": null,
                    "medium_image_url": null,
                    "large_image_url": null,
                    "maximum_image_url": null
                }
            },
            "approved": true,
            "titles": [
                {
                    "type": "Default",
                    "title": "Sai Er Hao Season 7: Yuzhou Zhi Yan"
                },
                {
                    "type": "Synonym",
                    "title": "Seer Seventh Season"
                },
                {
                    "type": "Japanese",
                    "title": "\u8d5b\u5c14\u53f7\u7b2c7\u5b63\uff1a\u5b87\u5b99\u4e4b\u773c"
                }
            ],
            "title": "Sai Er Hao Season 7: Yuzhou Zhi Yan",
            "title_english": null,
            "title_japanese": "\u8d5b\u5c14\u53f7\u7b2c7\u5b63\uff1a\u5b87\u5b99\u4e4b\u773c",
            "title_synonyms": [
                "Seer Seventh Season"
            ],
            "type": "TV",
            "source": "Game",
            "episodes": 30,
            "status": "Finished Airing",
            "airing": false,
            "aired": {
                "from": "2016-06-03T00:00:00+00:00",
                "to": "2016-09-17T00:00:00+00:00",
                "prop": {
                    "from": {
                        "day": 3,
                        "month": 6,
                        "year": 2016
                    },
                    "to": {
                        "day": 17,
                        "month": 9,
                        "year": 2016
                    }
                },
                "string": "Jun 3, 2016 to Sep 17, 2016"
            },
            "duration": "15 min per ep",
            "rating": "PG - Children",
            "score": null,
            "scored_by": null,
            "rank": 19995,
            "popularity": 23807,
            "members": 189,
            "favorites": 0,
            "synopsis": null,
            "background": "",
            "season": "summer",
            "year": 2016,
            "broadcast": {
                "day": null,
                "time": null,
                "timezone": null,
                "string": "Unknown"
            },
            "producers": [],
            "licensors": [],
            "studios": [],
            "genres": [],
            "explicit_genres": [],
            "themes": [],
            "demographics": [
                {
                    "mal_id": 15,
                    "type": "anime",
                    "name": "Kids",
                    "url": "https://myanimelist.net/anime/genre/15/Kids"
                }
            ]
        },
        {
            "mal_id": 44151,
            "url": "https://myanimelist.net/anime/44151/Sai_Er_Hao_Season_8__Huanmeng_Zhan_Ji",
            "images": {
                "jpg": {
                    "image_url": "https://myanimelist.net/images/anime/1977/118000.jpg",
                    "small_image_url": "https://myanimelist.net/images/anime/1977/118000t.jpg",
                    "large_image_url": "https://myanimelist.net/images/anime/1977/118000l.jpg"
                },
                "webp": {
                    "image_url": "https://myanimelist.net/images/anime/1977/118000.webp",
                    "small_image_url": "https://myanimelist.net/images/anime/1977/118000t.webp",
                    "large_image_url": "https://myanimelist.net/images/anime/1977/118000l.webp"
                }
            },
            "trailer": {
                "youtube_id": null,
                "url": null,
                "embed_url": null,
                "images": {
                    "image_url": null,
                    "small_image_url": null,
                    "medium_image_url": null,
                    "large_image_url": null,
                    "maximum_image_url": null
                }
            },
            "approved": true,
            "titles": [
                {
                    "type": "Default",
                    "title": "Sai Er Hao Season 8: Huanmeng Zhan Ji"
                },
                {
                    "type": "Synonym",
                    "title": "Seer Eight Season"
                },
                {
                    "type": "Japanese",
                    "title": "\u8d5b\u5c14\u53f7\u7b2c8\u5b63\uff1a\u5e7b\u68a6\u6218\u8bb0"
                }
            ],
            "title": "Sai Er Hao Season 8: Huanmeng Zhan Ji",
            "title_english": null,
            "title_japanese": "\u8d5b\u5c14\u53f7\u7b2c8\u5b63\uff1a\u5e7b\u68a6\u6218\u8bb0",
            "title_synonyms": [
                "Seer Eight Season"
            ],
            "type": "TV",
            "source": "Game",
            "episodes": 30,
            "status": "Finished Airing",
            "airing": false,
            "aired": {
                "from": "2017-01-20T00:00:00+00:00",
                "to": "2017-08-18T00:00:00+00:00",
                "prop": {
                    "from": {
                        "day": 20,
                        "month": 1,
                        "year": 2017
                    },
                    "to": {
                        "day": 18,
                        "month": 8,
                        "year": 2017
                    }
                },
                "string": "Jan 20, 2017 to Aug 18, 2017"
            },
            "duration": "18 min per ep",
            "rating": "PG - Children",
            "score": null,
            "scored_by": null,
            "rank": 19996,
            "popularity": 23526,
            "members": 198,
            "favorites": 0,
            "synopsis": null,
            "background": "",
            "season": "winter",
            "year": 2017,
            "broadcast": {
                "day": null,
                "time": null,
                "timezone": null,
                "string": "Unknown"
            },
            "producers": [],
            "licensors": [],
            "studios": [],
            "genres": [],
            "explicit_genres": [],
            "themes": [],
            "demographics": [
                {
                    "mal_id": 15,
                    "type": "anime",
                    "name": "Kids",
                    "url": "https://myanimelist.net/anime/genre/15/Kids"
                }
            ]
        },
        {
            "mal_id": 44152,
            "url": "https://myanimelist.net/anime/44152/Sai_Er_Hao_Season_9__Pili_Jiuchong_Tian",
            "images": {
                "jpg": {
                    "image_url": "https://myanimelist.net/images/anime/1835/118001.jpg",
                    "small_image_url": "https://myanimelist.net/images/anime/1835/118001t.jpg",
                    "large_image_url": "https://myanimelist.net/images/anime/1835/118001l.jpg"
                },
                "webp": {
                    "image_url": "https://myanimelist.net/images/anime/1835/118001.webp",
                    "small_image_url": "https://myanimelist.net/images/anime/1835/118001t.webp",
                    "large_image_url": "https://myanimelist.net/images/anime/1835/118001l.webp"
                }
            },
            "trailer": {
                "youtube_id": null,
                "url": null,
                "embed_url": null,
                "images": {
                    "image_url": null,
                    "small_image_url": null,
                    "medium_image_url": null,
                    "large_image_url": null,
                    "maximum_image_url": null
                }
            },
            "approved": true,
            "titles": [
                {
                    "type": "Default",
                    "title": "Sai Er Hao Season 9: Pili Jiuchong Tian"
                },
                {
                    "type": "Synonym",
                    "title": "Seer Ninth Season"
                },
                {
                    "type": "Japanese",
                    "title": "\u8d5b\u5c14\u53f7\u7b2c9\u5b63\uff1a\u9739\u96f3\u4e5d\u91cd\u5929"
                }
            ],
            "title": "Sai Er Hao Season 9: Pili Jiuchong Tian",
            "title_english": null,
            "title_japanese": "\u8d5b\u5c14\u53f7\u7b2c9\u5b63\uff1a\u9739\u96f3\u4e5d\u91cd\u5929",
            "title_synonyms": [
                "Seer Ninth Season"
            ],
            "type": "TV",
            "source": "Game",
            "episodes": 30,
            "status": "Finished Airing",
            "airing": false,
            "aired": {
                "from": "2018-06-08T00:00:00+00:00",
                "to": "2018-09-28T00:00:00+00:00",
                "prop": {
                    "from": {
                        "day": 8,
                        "month": 6,
                        "year": 2018
                    },
                    "to": {
                        "day": 28,
                        "month": 9,
                        "year": 2018
                    }
                },
                "string": "Jun 8, 2018 to Sep 28, 2018"
            },
            "duration": "16 min per ep",
            "rating": "PG - Children",
            "score": null,
            "scored_by": null,
            "rank": 19997,
            "popularity": 24101,
            "members": 179,
            "favorites": 0,
            "synopsis": null,
            "background": "",
            "season": "summer",
            "year": 2018,
            "broadcast": {
                "day": null,
                "time": null,
                "timezone": null,
                "string": "Unknown"
            },
            "producers": [],
            "licensors": [],
            "studios": [],
            "genres": [],
            "explicit_genres": [],
            "themes": [],
            "demographics": [
                {
                    "mal_id": 15,
                    "type": "anime",
                    "name": "Kids",
                    "url": "https://myanimelist.net/anime/genre/15/Kids"
                }
            ]
        },
        {
            "mal_id": 44153,
            "url": "https://myanimelist.net/anime/44153/Sai_Er_Hao_Season_10__Bing_Feng_Yaosai",
            "images": {
                "jpg": {
                    "image_url": "https://myanimelist.net/images/anime/1842/118002.jpg",
                    "small_image_url": "https://myanimelist.net/images/anime/1842/118002t.jpg",
                    "large_image_url": "https://myanimelist.net/images/anime/1842/118002l.jpg"
                },
                "webp": {
                    "image_url": "https://myanimelist.net/images/anime/1842/118002.webp",
                    "small_image_url": "https://myanimelist.net/images/anime/1842/118002t.webp",
                    "large_image_url": "https://myanimelist.net/images/anime/1842/118002l.webp"
                }
            },
            "trailer": {
                "youtube_id": null,
                "url": null,
                "embed_url": null,
                "images": {
                    "image_url": null,
                    "small_image_url": null,
                    "medium_image_url": null,
                    "large_image_url": null,
                    "maximum_image_url": null
                }
            },
            "approved": true,
            "titles": [
                {
                    "type": "Default",
                    "title": "Sai Er Hao Season 10: Bing Feng Yaosai"
                },
                {
                    "type": "Synonym",
                    "title": "Seer Tenth Season"
                },
                {
                    "type": "Japanese",
                    "title": "\u8d5b\u5c14\u53f7\uff1a\u51b0\u5c01\u8981\u585e"
                }
            ],
            "title": "Sai Er Hao Season 10: Bing Feng Yaosai",
            "title_english": null,
            "title_japanese": "\u8d5b\u5c14\u53f7\uff1a\u51b0\u5c01\u8981\u585e",
            "title_synonyms": [
                "Seer Tenth Season"
            ],
            "type": "TV",
            "source": "Game",
            "episodes": 30,
            "status": "Finished Airing",
            "airing": false,
            "aired": {
                "from": "2019-05-30T00:00:00+00:00",
                "to": "2019-01-01T00:00:00+00:00",
                "prop": {
                    "from": {
                        "day": 30,
                        "month": 5,
                        "year": 2019
                    },
                    "to": {
                        "day": 1,
                        "month": 1,
                        "year": 2019
                    }
                },
                "string": "May 30, 2019 to 2019"
            },
            "duration": "15 min per ep",
            "rating": "PG - Children",
            "score": null,
            "scored_by": null,
            "rank": 19988,
            "popularity": 25663,
            "members": 137,
            "favorites": 0,
            "synopsis": null,
            "background": "",
            "season": null,
            "year": null,
            "broadcast": {
                "day": null,
                "time": null,
                "timezone": null,
                "string": "Unknown"
            },
            "producers": [],
            "licensors": [],
            "studios": [],
            "genres": [],
            "explicit_genres": [],
            "themes": [],
            "demographics": [
                {
                    "mal_id": 15,
                    "type": "anime",
                    "name": "Kids",
                    "url": "https://myanimelist.net/anime/genre/15/Kids"
                }
            ]
        },
        {
            "mal_id": 44154,
            "url": "https://myanimelist.net/anime/44154/Sai_Er_Hao_Movie_2__Leiyi_Yu_Mai_Er_Si",
            "images": {
                "jpg": {
                    "image_url": "https://myanimelist.net/images/anime/1683/117985.jpg",
                    "small_image_url": "https://myanimelist.net/images/anime/1683/117985t.jpg",
                    "large_image_url": "https://myanimelist.net/images/anime/1683/117985l.jpg"
                },
                "webp": {
                    "image_url": "https://myanimelist.net/images/anime/1683/117985.webp",
                    "small_image_url": "https://myanimelist.net/images/anime/1683/117985t.webp",
                    "large_image_url": "https://myanimelist.net/images/anime/1683/117985l.webp"
                }
            },
            "trailer": {
                "youtube_id": null,
                "url": null,
                "embed_url": null,
                "images": {
                    "image_url": null,
                    "small_image_url": null,
                    "medium_image_url": null,
                    "large_image_url": null,
                    "maximum_image_url": null
                }
            },
            "approved": true,
            "titles": [
                {
                    "type": "Default",
                    "title": "Sai Er Hao Movie 2: Leiyi Yu Mai Er Si"
                },
                {
                    "type": "Synonym",
                    "title": "Seer 2"
                },
                {
                    "type": "Japanese",
                    "title": "\u8d5b\u5c14\u53f7\u5927\u7535\u5f712\uff1a\u96f7\u4f0a\u4e0e\u8fc8\u5c14\u65af"
                }
            ],
            "title": "Sai Er Hao Movie 2: Leiyi Yu Mai Er Si",
            "title_english": null,
            "title_japanese": "\u8d5b\u5c14\u53f7\u5927\u7535\u5f712\uff1a\u96f7\u4f0a\u4e0e\u8fc8\u5c14\u65af",
            "title_synonyms": [
                "Seer 2"
            ],
            "type": "Movie",
            "source": "Game",
            "episodes": 1,
            "status": "Finished Airing",
            "airing": false,
            "aired": {
                "from": "2012-06-28T00:00:00+00:00",
                "to": null,
                "prop": {
                    "from": {
                        "day": 28,
                        "month": 6,
                        "year": 2012
                    },
                    "to": {
                        "day": null,
                        "month": null,
                        "year": null
                    }
                },
                "string": "Jun 28, 2012"
            },
            "duration": "1 hr 31 min",
            "rating": "PG - Children",
            "score": null,
            "scored_by": null,
            "rank": 19982,
            "popularity": 23892,
            "members": 186,
            "favorites": 0,
            "synopsis": null,
            "background": "",
            "season": null,
            "year": null,
            "broadcast": {
                "day": null,
                "time": null,
                "timezone": null,
                "string": null
            },
            "producers": [],
            "licensors": [],
            "studios": [],
            "genres": [],
            "explicit_genres": [],
            "themes": [],
            "demographics": [
                {
                    "mal_id": 15,
                    "type": "anime",
                    "name": "Kids",
                    "url": "https://myanimelist.net/anime/genre/15/Kids"
                }
            ]
        },
        {
            "mal_id": 44155,
            "url": "https://myanimelist.net/anime/44155/Sai_Er_Hao_Movie_3__Zhanshen_Lianmeng",
            "images": {
                "jpg": {
                    "image_url": "https://myanimelist.net/images/anime/1045/117986.jpg",
                    "small_image_url": "https://myanimelist.net/images/anime/1045/117986t.jpg",
                    "large_image_url": "https://myanimelist.net/images/anime/1045/117986l.jpg"
                },
                "webp": {
                    "image_url": "https://myanimelist.net/images/anime/1045/117986.webp",
                    "small_image_url": "https://myanimelist.net/images/anime/1045/117986t.webp",
                    "large_image_url": "https://myanimelist.net/images/anime/1045/117986l.webp"
                }
            },
            "trailer": {
                "youtube_id": null,
                "url": null,
                "embed_url": null,
                "images": {
                    "image_url": null,
                    "small_image_url": null,
                    "medium_image_url": null,
                    "large_image_url": null,
                    "maximum_image_url": null
                }
            },
            "approved": true,
            "titles": [
                {
                    "type": "Default",
                    "title": "Sai Er Hao Movie 3: Zhanshen Lianmeng"
                },
                {
                    "type": "Synonym",
                    "title": "Seer Movie 3: Heroes Alliance"
                },
                {
                    "type": "Japanese",
                    "title": "\u8d5b\u5c14\u53f7\u5927\u7535\u5f713\uff1a\u6218\u795e\u8054\u76df"
                }
            ],
            "title": "Sai Er Hao Movie 3: Zhanshen Lianmeng",
            "title_english": null,
            "title_japanese": "\u8d5b\u5c14\u53f7\u5927\u7535\u5f713\uff1a\u6218\u795e\u8054\u76df",
            "title_synonyms": [
                "Seer Movie 3: Heroes Alliance"
            ],
            "type": "Movie",
            "source": "Game",
            "episodes": 1,
            "status": "Finished Airing",
            "airing": false,
            "aired": {
                "from": "2013-07-12T00:00:00+00:00",
                "to": null,
                "prop": {
                    "from": {
                        "day": 12,
                        "month": 7,
                        "year": 2013
                    },
                    "to": {
                        "day": null,
                        "month": null,
                        "year": null
                    }
                },
                "string": "Jul 12, 2013"
            },
            "duration": "1 hr 41 min",
            "rating": "PG - Children",
            "score": null,
            "scored_by": null,
            "rank": 19983,
            "popularity": 24381,
            "members": 170,
            "favorites": 0,
            "synopsis": null,
            "background": "",
            "season": null,
            "year": null,
            "broadcast": {
                "day": null,
                "time": null,
                "timezone": null,
                "string": null
            },
            "producers": [],
            "licensors": [],
            "studios": [],
            "genres": [],
            "explicit_genres": [],
            "themes": [],
            "demographics": [
                {
                    "mal_id": 15,
                    "type": "anime",
                    "name": "Kids",
                    "url": "https://myanimelist.net/anime/genre/15/Kids"
                }
            ]
        },
        {
            "mal_id": 44156,
            "url": "https://myanimelist.net/anime/44156/Sai_Er_Hao_Movie_4__Sheng_Mo_Zhi_Zhan",
            "images": {
                "jpg": {
                    "image_url": "https://myanimelist.net/images/anime/1377/117987.jpg",
                    "small_image_url": "https://myanimelist.net/images/anime/1377/117987t.jpg",
                    "large_image_url": "https://myanimelist.net/images/anime/1377/117987l.jpg"
                },
                "webp": {
                    "image_url": "https://myanimelist.net/images/anime/1377/117987.webp",
                    "small_image_url": "https://myanimelist.net/images/anime/1377/117987t.webp",
                    "large_image_url": "https://myanimelist.net/images/anime/1377/117987l.webp"
                }
            },
            "trailer": {
                "youtube_id": null,
                "url": null,
                "embed_url": null,
                "images": {
                    "image_url": null,
                    "small_image_url": null,
                    "medium_image_url": null,
                    "large_image_url": null,
                    "maximum_image_url": null
                }
            },
            "approved": true,
            "titles": [
                {
                    "type": "Default",
                    "title": "Sai Er Hao Movie 4: Sheng Mo Zhi Zhan"
                },
                {
                    "type": "Synonym",
                    "title": "Seer Movie 4: Trinity War"
                },
                {
                    "type": "Japanese",
                    "title": "\u8d5b\u5c14\u53f7\u5927\u7535\u5f714\uff1a\u5723\u9b54\u4e4b\u6218"
                }
            ],
            "title": "Sai Er Hao Movie 4: Sheng Mo Zhi Zhan",
            "title_english": null,
            "title_japanese": "\u8d5b\u5c14\u53f7\u5927\u7535\u5f714\uff1a\u5723\u9b54\u4e4b\u6218",
            "title_synonyms": [
                "Seer Movie 4: Trinity War"
            ],
            "type": "Movie",
            "source": "Game",
            "episodes": 1,
            "status": "Finished Airing",
            "airing": false,
            "aired": {
                "from": "2014-07-10T00:00:00+00:00",
                "to": null,
                "prop": {
                    "from": {
                        "day": 10,
                        "month": 7,
                        "year": 2014
                    },
                    "to": {
                        "day": null,
                        "month": null,
                        "year": null
                    }
                },
                "string": "Jul 10, 2014"
            },
            "duration": "1 hr 37 min",
            "rating": "PG - Children",
            "score": null,
            "scored_by": null,
            "rank": 19984,
            "popularity": 24472,
            "members": 167,
            "favorites": 0,
            "synopsis": null,
            "background": "",
            "season": null,
            "year": null,
            "broadcast": {
                "day": null,
                "time": null,
                "timezone": null,
                "string": null
            },
            "producers": [],
            "licensors": [],
            "studios": [],
            "genres": [],
            "explicit_genres": [],
            "themes": [],
            "demographics": [
                {
                    "mal_id": 15,
                    "type": "anime",
                    "name": "Kids",
                    "url": "https://myanimelist.net/anime/genre/15/Kids"
                }
            ]
        },
        {
            "mal_id": 44157,
            "url": "https://myanimelist.net/anime/44157/Sai_Er_Hao_Movie_5__Leishen_Jue_Qi",
            "images": {
                "jpg": {
                    "image_url": "https://myanimelist.net/images/anime/1326/117989.jpg",
                    "small_image_url": "https://myanimelist.net/images/anime/1326/117989t.jpg",
                    "large_image_url": "https://myanimelist.net/images/anime/1326/117989l.jpg"
                },
                "webp": {
                    "image_url": "https://myanimelist.net/images/anime/1326/117989.webp",
                    "small_image_url": "https://myanimelist.net/images/anime/1326/117989t.webp",
                    "large_image_url": "https://myanimelist.net/images/anime/1326/117989l.webp"
                }
            },
            "trailer": {
                "youtube_id": null,
                "url": null,
                "embed_url": null,
                "images": {
                    "image_url": null,
                    "small_image_url": null,
                    "medium_image_url": null,
                    "large_image_url": null,
                    "maximum_image_url": null
                }
            },
            "approved": true,
            "titles": [
                {
                    "type": "Default",
                    "title": "Sai Er Hao Movie 5: Leishen Jue Qi"
                },
                {
                    "type": "Synonym",
                    "title": "Seer Movie 5: Rise of Thunder"
                },
                {
                    "type": "Japanese",
                    "title": "\u8d5b\u5c14\u53f7\u5927\u7535\u5f715\uff1a\u96f7\u795e\u5d1b\u8d77"
                }
            ],
            "title": "Sai Er Hao Movie 5: Leishen Jue Qi",
            "title_english": null,
            "title_japanese": "\u8d5b\u5c14\u53f7\u5927\u7535\u5f715\uff1a\u96f7\u795e\u5d1b\u8d77",
            "title_synonyms": [
                "Seer Movie 5: Rise of Thunder"
            ],
            "type": "Movie",
            "source": "Game",
            "episodes": 1,
            "status": "Finished Airing",
            "airing": false,
            "aired": {
                "from": "2015-07-23T00:00:00+00:00",
                "to": null,
                "prop": {
                    "from": {
                        "day": 23,
                        "month": 7,
                        "year": 2015
                    },
                    "to": {
                        "day": null,
                        "month": null,
                        "year": null
                    }
                },
                "string": "Jul 23, 2015"
            },
            "duration": "1 hr 41 min",
            "rating": "PG - Children",
            "score": null,
            "scored_by": null,
            "rank": 19985,
            "popularity": 24672,
            "members": 161,
            "favorites": 0,
            "synopsis": null,
            "background": "",
            "season": null,
            "year": null,
            "broadcast": {
                "day": null,
                "time": null,
                "timezone": null,
                "string": null
            },
            "producers": [],
            "licensors": [],
            "studios": [],
            "genres": [],
            "explicit_genres": [],
            "themes": [],
            "demographics": [
                {
                    "mal_id": 15,
                    "type": "anime",
                    "name": "Kids",
                    "url": "https://myanimelist.net/anime/genre/15/Kids"
                }
            ]
        },
        {
            "mal_id": 44158,
            "url": "https://myanimelist.net/anime/44158/Sai_Er_Hao_Movie_6__Sheng_Zhe_Wudi",
            "images": {
                "jpg": {
                    "image_url": "https://myanimelist.net/images/anime/1553/117990.jpg",
                    "small_image_url": "https://myanimelist.net/images/anime/1553/117990t.jpg",
                    "large_image_url": "https://myanimelist.net/images/anime/1553/117990l.jpg"
                },
                "webp": {
                    "image_url": "https://myanimelist.net/images/anime/1553/117990.webp",
                    "small_image_url": "https://myanimelist.net/images/anime/1553/117990t.webp",
                    "large_image_url": "https://myanimelist.net/images/anime/1553/117990l.webp"
                }
            },
            "trailer": {
                "youtube_id": null,
                "url": null,
                "embed_url": null,
                "images": {
                    "image_url": null,
                    "small_image_url": null,
                    "medium_image_url": null,
                    "large_image_url": null,
                    "maximum_image_url": null
                }
            },
            "approved": true,
            "titles": [
                {
                    "type": "Default",
                    "title": "Sai Er Hao Movie 6: Sheng Zhe Wudi"
                },
                {
                    "type": "Synonym",
                    "title": "Seer Movie 6: Invincible Puni"
                },
                {
                    "type": "Japanese",
                    "title": "\u8d5b\u5c14\u53f7\u5927\u7535\u5f716\uff1a\u5723\u8005\u65e0\u654c"
                }
            ],
            "title": "Sai Er Hao Movie 6: Sheng Zhe Wudi",
            "title_english": null,
            "title_japanese": "\u8d5b\u5c14\u53f7\u5927\u7535\u5f716\uff1a\u5723\u8005\u65e0\u654c",
            "title_synonyms": [
                "Seer Movie 6: Invincible Puni"
            ],
            "type": "Movie",
            "source": "Game",
            "episodes": 1,
            "status": "Finished Airing",
            "airing": false,
            "aired": {
                "from": "2018-09-08T00:00:00+00:00",
                "to": null,
                "prop": {
                    "from": {
                        "day": 8,
                        "month": 9,
                        "year": 2018
                    },
                    "to": {
                        "day": null,
                        "month": null,
                        "year": null
                    }
                },
                "string": "Sep 8, 2018"
            },
            "duration": "1 hr 39 min",
            "rating": "PG - Children",
            "score": null,
            "scored_by": null,
            "rank": 19986,
            "popularity": 24541,
            "members": 165,
            "favorites": 0,
            "synopsis": null,
            "background": "",
            "season": null,
            "year": null,
            "broadcast": {
                "day": null,
                "time": null,
                "timezone": null,
                "string": null
            },
            "producers": [],
            "licensors": [],
            "studios": [],
            "genres": [],
            "explicit_genres": [],
            "themes": [],
            "demographics": [
                {
                    "mal_id": 15,
                    "type": "anime",
                    "name": "Kids",
                    "url": "https://myanimelist.net/anime/genre/15/Kids"
                }
            ]
        },
        {
            "mal_id": 44159,
            "url": "https://myanimelist.net/anime/44159/Sai_Er_Hao_Movie_7__Fengkuang_Jiqi_Cheng",
            "images": {
                "jpg": {
                    "image_url": "https://myanimelist.net/images/anime/1121/117991.jpg",
                    "small_image_url": "https://myanimelist.net/images/anime/1121/117991t.jpg",
                    "large_image_url": "https://myanimelist.net/images/anime/1121/117991l.jpg"
                },
                "webp": {
                    "image_url": "https://myanimelist.net/images/anime/1121/117991.webp",
                    "small_image_url": "https://myanimelist.net/images/anime/1121/117991t.webp",
                    "large_image_url": "https://myanimelist.net/images/anime/1121/117991l.webp"
                }
            },
            "trailer": {
                "youtube_id": null,
                "url": null,
                "embed_url": null,
                "images": {
                    "image_url": null,
                    "small_image_url": null,
                    "medium_image_url": null,
                    "large_image_url": null,
                    "maximum_image_url": null
                }
            },
            "approved": true,
            "titles": [
                {
                    "type": "Default",
                    "title": "Sai Er Hao Movie 7: Fengkuang Jiqi Cheng"
                },
                {
                    "type": "Synonym",
                    "title": "Seer Movie 7: Crazy Intelligence"
                },
                {
                    "type": "Japanese",
                    "title": "\u8d5b\u5c14\u53f7\u5927\u7535\u5f717\uff1a\u75af\u72c2\u673a\u5668\u57ce"
                }
            ],
            "title": "Sai Er Hao Movie 7: Fengkuang Jiqi Cheng",
            "title_english": null,
            "title_japanese": "\u8d5b\u5c14\u53f7\u5927\u7535\u5f717\uff1a\u75af\u72c2\u673a\u5668\u57ce",
            "title_synonyms": [
                "Seer Movie 7: Crazy Intelligence"
            ],
            "type": "Movie",
            "source": "Game",
            "episodes": 1,
            "status": "Finished Airing",
            "airing": false,
            "aired": {
                "from": "2019-08-02T00:00:00+00:00",
                "to": null,
                "prop": {
                    "from": {
                        "day": 2,
                        "month": 8,
                        "year": 2019
                    },
                    "to": {
                        "day": null,
                        "month": null,
                        "year": null
                    }
                },
                "string": "Aug 2, 2019"
            },
            "duration": "1 hr 38 min",
            "rating": "PG - Children",
            "score": null,
            "scored_by": null,
            "rank": 19987,
            "popularity": 24863,
            "members": 156,
            "favorites": 0,
            "synopsis": null,
            "background": "",
            "season": null,
            "year": null,
            "broadcast": {
                "day": null,
                "time": null,
                "timezone": null,
                "string": null
            },
            "producers": [
                {
                    "mal_id": 2216,
                    "type": "anime",
                    "name": "CMAY Animation",
                    "url": "https://myanimelist.net/anime/producer/2216/CMAY_Animation"
                }
            ],
            "licensors": [],
            "studios": [
                {
                    "mal_id": 2075,
                    "type": "anime",
                    "name": "TaoMee Inc.",
                    "url": "https://myanimelist.net/anime/producer/2075/TaoMee_Inc"
                }
            ],
            "genres": [
                {
                    "mal_id": 2,
                    "type": "anime",
                    "name": "Adventure",
                    "url": "https://myanimelist.net/anime/genre/2/Adventure"
                }
            ],
            "explicit_genres": [],
            "themes": [],
            "demographics": [
                {
                    "mal_id": 15,
                    "type": "anime",
                    "name": "Kids",
                    "url": "https://myanimelist.net/anime/genre/15/Kids"
                }
            ]
        },
        {
            "mal_id": 44160,
            "url": "https://myanimelist.net/anime/44160/Mole_Zhuang_Yuan__Shiqian_Ji",
            "images": {
                "jpg": {
                    "image_url": "https://myanimelist.net/images/anime/1748/118009.jpg",
                    "small_image_url": "https://myanimelist.net/images/anime/1748/118009t.jpg",
                    "large_image_url": "https://myanimelist.net/images/anime/1748/118009l.jpg"
                },
                "webp": {
                    "image_url": "https://myanimelist.net/images/anime/1748/118009.webp",
                    "small_image_url": "https://myanimelist.net/images/anime/1748/118009t.webp",
                    "large_image_url": "https://myanimelist.net/images/anime/1748/118009l.webp"
                }
            },
            "trailer": {
                "youtube_id": null,
                "url": null,
                "embed_url": null,
                "images": {
                    "image_url": null,
                    "small_image_url": null,
                    "medium_image_url": null,
                    "large_image_url": null,
                    "maximum_image_url": null
                }
            },
            "approved": true,
            "titles": [
                {
                    "type": "Default",
                    "title": "Mole Zhuang Yuan: Shiqian Ji"
                },
                {
                    "type": "Synonym",
                    "title": "Moer Zhuangyuan: Shiqian Ji"
                },
                {
                    "type": "Japanese",
                    "title": "\u6469\u5c14\u5e84\u56ed \u53f2\u524d\u5b63"
                }
            ],
            "title": "Mole Zhuang Yuan: Shiqian Ji",
            "title_english": null,
            "title_japanese": "\u6469\u5c14\u5e84\u56ed \u53f2\u524d\u5b63",
            "title_synonyms": [
                "Moer Zhuangyuan: Shiqian Ji"
            ],
            "type": "ONA",
            "source": "Game",
            "episodes": 20,
            "status": "Finished Airing",
            "airing": false,
            "aired": {
                "from": "2009-01-01T00:00:00+00:00",
                "to": null,
                "prop": {
                    "from": {
                        "day": 1,
                        "month": 1,
                        "year": 2009
                    },
                    "to": {
                        "day": null,
                        "month": null,
                        "year": null
                    }
                },
                "string": "2009 to ?"
            },
            "duration": "5 min per ep",
            "rating": "PG - Children",
            "score": null,
            "scored_by": null,
            "rank": 18899,
            "popularity": 26957,
            "members": 115,
            "favorites": 0,
            "synopsis": null,
            "background": "",
            "season": null,
            "year": null,
            "broadcast": {
                "day": null,
                "time": null,
                "timezone": null,
                "string": null
            },
            "producers": [],
            "licensors": [],
            "studios": [],
            "genres": [],
            "explicit_genres": [],
            "themes": [],
            "demographics": [
                {
                    "mal_id": 15,
                    "type": "anime",
                    "name": "Kids",
                    "url": "https://myanimelist.net/anime/genre/15/Kids"
                }
            ]
        },
        {
            "mal_id": 44161,
            "url": "https://myanimelist.net/anime/44161/Mole_Zhuang_Yuan__Zhou_Bo_Ju",
            "images": {
                "jpg": {
                    "image_url": "https://myanimelist.net/images/anime/1693/118010.jpg",
                    "small_image_url": "https://myanimelist.net/images/anime/1693/118010t.jpg",
                    "large_image_url": "https://myanimelist.net/images/anime/1693/118010l.jpg"
                },
                "webp": {
                    "image_url": "https://myanimelist.net/images/anime/1693/118010.webp",
                    "small_image_url": "https://myanimelist.net/images/anime/1693/118010t.webp",
                    "large_image_url": "https://myanimelist.net/images/anime/1693/118010l.webp"
                }
            },
            "trailer": {
                "youtube_id": null,
                "url": null,
                "embed_url": null,
                "images": {
                    "image_url": null,
                    "small_image_url": null,
                    "medium_image_url": null,
                    "large_image_url": null,
                    "maximum_image_url": null
                }
            },
            "approved": true,
            "titles": [
                {
                    "type": "Default",
                    "title": "Mole Zhuang Yuan: Zhou Bo Ju"
                },
                {
                    "type": "Synonym",
                    "title": "Mole Manor"
                },
                {
                    "type": "Synonym",
                    "title": "Moer Zhuangyuan Zhou Bo Ju"
                },
                {
                    "type": "Japanese",
                    "title": "\u6469\u5c14\u5e84\u56ed\u5468\u64ad\u5267"
                }
            ],
            "title": "Mole Zhuang Yuan: Zhou Bo Ju",
            "title_english": null,
            "title_japanese": "\u6469\u5c14\u5e84\u56ed\u5468\u64ad\u5267",
            "title_synonyms": [
                "Mole Manor",
                "Moer Zhuangyuan Zhou Bo Ju"
            ],
            "type": "ONA",
            "source": "Game",
            "episodes": 9,
            "status": "Finished Airing",
            "airing": false,
            "aired": {
                "from": "2012-04-28T00:00:00+00:00",
                "to": "2012-06-30T00:00:00+00:00",
                "prop": {
                    "from": {
                        "day": 28,
                        "month": 4,
                        "year": 2012
                    },
                    "to": {
                        "day": 30,
                        "month": 6,
                        "year": 2012
                    }
                },
                "string": "Apr 28, 2012 to Jun 30, 2012"
            },
            "duration": "10 min per ep",
            "rating": "PG - Children",
            "score": null,
            "scored_by": null,
            "rank": 18900,
            "popularity": 24966,
            "members": 153,
            "favorites": 0,
            "synopsis": null,
            "background": "",
            "season": null,
            "year": null,
            "broadcast": {
                "day": null,
                "time": null,
                "timezone": null,
                "string": null
            },
            "producers": [],
            "licensors": [],
            "studios": [],
            "genres": [],
            "explicit_genres": [],
            "themes": [],
            "demographics": [
                {
                    "mal_id": 15,
                    "type": "anime",
                    "name": "Kids",
                    "url": "https://myanimelist.net/anime/genre/15/Kids"
                }
            ]
        },
        {
            "mal_id": 44162,
            "url": "https://myanimelist.net/anime/44162/Mole_Zhuang_Yuan",
            "images": {
                "jpg": {
                    "image_url": "https://myanimelist.net/images/anime/1946/118005.jpg",
                    "small_image_url": "https://myanimelist.net/images/anime/1946/118005t.jpg",
                    "large_image_url": "https://myanimelist.net/images/anime/1946/118005l.jpg"
                },
                "webp": {
                    "image_url": "https://myanimelist.net/images/anime/1946/118005.webp",
                    "small_image_url": "https://myanimelist.net/images/anime/1946/118005t.webp",
                    "large_image_url": "https://myanimelist.net/images/anime/1946/118005l.webp"
                }
            },
            "trailer": {
                "youtube_id": null,
                "url": null,
                "embed_url": null,
                "images": {
                    "image_url": null,
                    "small_image_url": null,
                    "medium_image_url": null,
                    "large_image_url": null,
                    "maximum_image_url": null
                }
            },
            "approved": true,
            "titles": [
                {
                    "type": "Default",
                    "title": "Mole Zhuang Yuan"
                },
                {
                    "type": "Synonym",
                    "title": "Mole's World"
                },
                {
                    "type": "Synonym",
                    "title": "Mole Manor"
                },
                {
                    "type": "Japanese",
                    "title": "\u6469\u5c14\u5e84\u56ed"
                }
            ],
            "title": "Mole Zhuang Yuan",
            "title_english": null,
            "title_japanese": "\u6469\u5c14\u5e84\u56ed",
            "title_synonyms": [
                "Mole's World",
                "Mole Manor"
            ],
            "type": "TV",
            "source": "Game",
            "episodes": 52,
            "status": "Finished Airing",
            "airing": false,
            "aired": {
                "from": "2011-06-20T00:00:00+00:00",
                "to": "2011-01-01T00:00:00+00:00",
                "prop": {
                    "from": {
                        "day": 20,
                        "month": 6,
                        "year": 2011
                    },
                    "to": {
                        "day": 1,
                        "month": 1,
                        "year": 2011
                    }
                },
                "string": "Jun 20, 2011 to 2011"
            },
            "duration": "12 min per ep",
            "rating": "PG - Children",
            "score": null,
            "scored_by": null,
            "rank": 18893,
            "popularity": 25566,
            "members": 139,
            "favorites": 0,
            "synopsis": null,
            "background": "",
            "season": null,
            "year": null,
            "broadcast": {
                "day": null,
                "time": null,
                "timezone": null,
                "string": "Unknown"
            },
            "producers": [],
            "licensors": [],
            "studios": [],
            "genres": [],
            "explicit_genres": [],
            "themes": [],
            "demographics": [
                {
                    "mal_id": 15,
                    "type": "anime",
                    "name": "Kids",
                    "url": "https://myanimelist.net/anime/genre/15/Kids"
                }
            ]
        },
        {
            "mal_id": 44163,
            "url": "https://myanimelist.net/anime/44163/Mole_Zhuang_Yuan_2nd_Season",
            "images": {
                "jpg": {
                    "image_url": "https://myanimelist.net/images/anime/1609/118007.jpg",
                    "small_image_url": "https://myanimelist.net/images/anime/1609/118007t.jpg",
                    "large_image_url": "https://myanimelist.net/images/anime/1609/118007l.jpg"
                },
                "webp": {
                    "image_url": "https://myanimelist.net/images/anime/1609/118007.webp",
                    "small_image_url": "https://myanimelist.net/images/anime/1609/118007t.webp",
                    "large_image_url": "https://myanimelist.net/images/anime/1609/118007l.webp"
                }
            },
            "trailer": {
                "youtube_id": null,
                "url": null,
                "embed_url": null,
                "images": {
                    "image_url": null,
                    "small_image_url": null,
                    "medium_image_url": null,
                    "large_image_url": null,
                    "maximum_image_url": null
                }
            },
            "approved": true,
            "titles": [
                {
                    "type": "Default",
                    "title": "Mole Zhuang Yuan 2nd Season"
                },
                {
                    "type": "Japanese",
                    "title": "\u6469\u5c14\u5e84\u56ed\u7b2c\u4e8c\u5b63"
                }
            ],
            "title": "Mole Zhuang Yuan 2nd Season",
            "title_english": null,
            "title_japanese": "\u6469\u5c14\u5e84\u56ed\u7b2c\u4e8c\u5b63",
            "title_synonyms": [],
            "type": "TV",
            "source": "Game",
            "episodes": 52,
            "status": "Finished Airing",
            "airing": false,
            "aired": {
                "from": "2012-03-10T00:00:00+00:00",
                "to": "2012-01-01T00:00:00+00:00",
                "prop": {
                    "from": {
                        "day": 10,
                        "month": 3,
                        "year": 2012
                    },
                    "to": {
                        "day": 1,
                        "month": 1,
                        "year": 2012
                    }
                },
                "string": "Mar 10, 2012 to 2012"
            },
            "duration": "12 min per ep",
            "rating": "PG - Children",
            "score": null,
            "scored_by": null,
            "rank": 18894,
            "popularity": 26695,
            "members": 119,
            "favorites": 0,
            "synopsis": null,
            "background": "",
            "season": null,
            "year": null,
            "broadcast": {
                "day": null,
                "time": null,
                "timezone": null,
                "string": "Unknown"
            },
            "producers": [],
            "licensors": [],
            "studios": [],
            "genres": [],
            "explicit_genres": [],
            "themes": [],
            "demographics": [
                {
                    "mal_id": 15,
                    "type": "anime",
                    "name": "Kids",
                    "url": "https://myanimelist.net/anime/genre/15/Kids"
                }
            ]
        },
        {
            "mal_id": 44164,
            "url": "https://myanimelist.net/anime/44164/Mole_Zhuang_Yuan_3rd_Season",
            "images": {
                "jpg": {
                    "image_url": "https://myanimelist.net/images/anime/1055/118008.jpg",
                    "small_image_url": "https://myanimelist.net/images/anime/1055/118008t.jpg",
                    "large_image_url": "https://myanimelist.net/images/anime/1055/118008l.jpg"
                },
                "webp": {
                    "image_url": "https://myanimelist.net/images/anime/1055/118008.webp",
                    "small_image_url": "https://myanimelist.net/images/anime/1055/118008t.webp",
                    "large_image_url": "https://myanimelist.net/images/anime/1055/118008l.webp"
                }
            },
            "trailer": {
                "youtube_id": null,
                "url": null,
                "embed_url": null,
                "images": {
                    "image_url": null,
                    "small_image_url": null,
                    "medium_image_url": null,
                    "large_image_url": null,
                    "maximum_image_url": null
                }
            },
            "approved": true,
            "titles": [
                {
                    "type": "Default",
                    "title": "Mole Zhuang Yuan 3rd Season"
                },
                {
                    "type": "Japanese",
                    "title": "\u6469\u5c14\u5e84\u56ed\u7b2c\u4e09\u5b63"
                }
            ],
            "title": "Mole Zhuang Yuan 3rd Season",
            "title_english": null,
            "title_japanese": "\u6469\u5c14\u5e84\u56ed\u7b2c\u4e09\u5b63",
            "title_synonyms": [],
            "type": "TV",
            "source": "Game",
            "episodes": 52,
            "status": "Finished Airing",
            "airing": false,
            "aired": {
                "from": "2013-03-16T00:00:00+00:00",
                "to": "2013-01-01T00:00:00+00:00",
                "prop": {
                    "from": {
                        "day": 16,
                        "month": 3,
                        "year": 2013
                    },
                    "to": {
                        "day": 1,
                        "month": 1,
                        "year": 2013
                    }
                },
                "string": "Mar 16, 2013 to 2013"
            },
            "duration": "12 min per ep",
            "rating": "PG - Children",
            "score": null,
            "scored_by": null,
            "rank": 18896,
            "popularity": 26825,
            "members": 117,
            "favorites": 0,
            "synopsis": null,
            "background": "",
            "season": null,
            "year": null,
            "broadcast": {
                "day": null,
                "time": null,
                "timezone": null,
                "string": "Unknown"
            },
            "producers": [],
            "licensors": [],
            "studios": [],
            "genres": [],
            "explicit_genres": [],
            "themes": [],
            "demographics": [
                {
                    "mal_id": 15,
                    "type": "anime",
                    "name": "Kids",
                    "url": "https://myanimelist.net/anime/genre/15/Kids"
                }
            ]
        },
        {
            "mal_id": 44165,
            "url": "https://myanimelist.net/anime/44165/Mole_Zhuang_Yuan_3__Mohuan_Lieche_Da_Maoxian",
            "images": {
                "jpg": {
                    "image_url": "https://myanimelist.net/images/anime/1934/118004.jpg",
                    "small_image_url": "https://myanimelist.net/images/anime/1934/118004t.jpg",
                    "large_image_url": "https://myanimelist.net/images/anime/1934/118004l.jpg"
                },
                "webp": {
                    "image_url": "https://myanimelist.net/images/anime/1934/118004.webp",
                    "small_image_url": "https://myanimelist.net/images/anime/1934/118004t.webp",
                    "large_image_url": "https://myanimelist.net/images/anime/1934/118004l.webp"
                }
            },
            "trailer": {
                "youtube_id": null,
                "url": null,
                "embed_url": null,
                "images": {
                    "image_url": null,
                    "small_image_url": null,
                    "medium_image_url": null,
                    "large_image_url": null,
                    "maximum_image_url": null
                }
            },
            "approved": true,
            "titles": [
                {
                    "type": "Default",
                    "title": "Mole Zhuang Yuan 3: Mohuan Lieche Da Maoxian"
                },
                {
                    "type": "Japanese",
                    "title": "\u6469\u5c14\u5e84\u56ed\u5927\u7535\u5f713\uff1a\u9b54\u5e7b\u5217\u8f66\u5927\u5192\u9669"
                },
                {
                    "type": "English",
                    "title": "Legend Of The Moles: The Magic Train Adventure"
                }
            ],
            "title": "Mole Zhuang Yuan 3: Mohuan Lieche Da Maoxian",
            "title_english": "Legend Of The Moles: The Magic Train Adventure",
            "title_japanese": "\u6469\u5c14\u5e84\u56ed\u5927\u7535\u5f713\uff1a\u9b54\u5e7b\u5217\u8f66\u5927\u5192\u9669",
            "title_synonyms": [],
            "type": "Movie",
            "source": "Game",
            "episodes": 1,
            "status": "Finished Airing",
            "airing": false,
            "aired": {
                "from": "2015-02-05T00:00:00+00:00",
                "to": null,
                "prop": {
                    "from": {
                        "day": 5,
                        "month": 2,
                        "year": 2015
                    },
                    "to": {
                        "day": null,
                        "month": null,
                        "year": null
                    }
                },
                "string": "Feb 5, 2015"
            },
            "duration": "1 hr 27 min",
            "rating": "PG - Children",
            "score": null,
            "scored_by": null,
            "rank": 18895,
            "popularity": 25175,
            "members": 148,
            "favorites": 0,
            "synopsis": null,
            "background": "",
            "season": null,
            "year": null,
            "broadcast": {
                "day": null,
                "time": null,
                "timezone": null,
                "string": null
            },
            "producers": [],
            "licensors": [],
            "studios": [],
            "genres": [],
            "explicit_genres": [],
            "themes": [],
            "demographics": [
                {
                    "mal_id": 15,
                    "type": "anime",
                    "name": "Kids",
                    "url": "https://myanimelist.net/anime/genre/15/Kids"
                }
            ]
        },
        {
            "mal_id": 44166,
            "url": "https://myanimelist.net/anime/44166/Xiaohu_Huan_Xiang",
            "images": {
                "jpg": {
                    "image_url": "https://myanimelist.net/images/anime/1228/118016.jpg",
                    "small_image_url": "https://myanimelist.net/images/anime/1228/118016t.jpg",
                    "large_image_url": "https://myanimelist.net/images/anime/1228/118016l.jpg"
                },
                "webp": {
                    "image_url": "https://myanimelist.net/images/anime/1228/118016.webp",
                    "small_image_url": "https://myanimelist.net/images/anime/1228/118016t.webp",
                    "large_image_url": "https://myanimelist.net/images/anime/1228/118016l.webp"
                }
            },
            "trailer": {
                "youtube_id": null,
                "url": null,
                "embed_url": null,
                "images": {
                    "image_url": null,
                    "small_image_url": null,
                    "medium_image_url": null,
                    "large_image_url": null,
                    "maximum_image_url": null
                }
            },
            "approved": true,
            "titles": [
                {
                    "type": "Default",
                    "title": "Xiaohu Huan Xiang"
                },
                {
                    "type": "Japanese",
                    "title": "\u5c0f\u864e\u8fd8\u4e61"
                }
            ],
            "title": "Xiaohu Huan Xiang",
            "title_english": null,
            "title_japanese": "\u5c0f\u864e\u8fd8\u4e61",
            "title_synonyms": [],
            "type": "TV",
            "source": "Unknown",
            "episodes": 78,
            "status": "Finished Airing",
            "airing": false,
            "aired": {
                "from": "2001-01-01T00:00:00+00:00",
                "to": null,
                "prop": {
                    "from": {
                        "day": 1,
                        "month": 1,
                        "year": 2001
                    },
                    "to": {
                        "day": null,
                        "month": null,
                        "year": null
                    }
                },
                "string": "2001 to ?"
            },
            "duration": "22 min per ep",
            "rating": "PG - Children",
            "score": null,
            "scored_by": null,
            "rank": 21839,
            "popularity": 27183,
            "members": 112,
            "favorites": 0,
            "synopsis": null,
            "background": "",
            "season": null,
            "year": null,
            "broadcast": {
                "day": null,
                "time": null,
                "timezone": null,
                "string": "Unknown"
            },
            "producers": [],
            "licensors": [],
            "studios": [],
            "genres": [],
            "explicit_genres": [],
            "themes": [],
            "demographics": [
                {
                    "mal_id": 15,
                    "type": "anime",
                    "name": "Kids",
                    "url": "https://myanimelist.net/anime/genre/15/Kids"
                }
            ]
        },
        {
            "mal_id": 44167,
            "url": "https://myanimelist.net/anime/44167/Meng_Li_Ren",
            "images": {
                "jpg": {
                    "image_url": "https://myanimelist.net/images/anime/1775/118017.jpg",
                    "small_image_url": "https://myanimelist.net/images/anime/1775/118017t.jpg",
                    "large_image_url": "https://myanimelist.net/images/anime/1775/118017l.jpg"
                },
                "webp": {
                    "image_url": "https://myanimelist.net/images/anime/1775/118017.webp",
                    "small_image_url": "https://myanimelist.net/images/anime/1775/118017t.webp",
                    "large_image_url": "https://myanimelist.net/images/anime/1775/118017l.webp"
                }
            },
            "trailer": {
                "youtube_id": null,
                "url": null,
                "embed_url": null,
                "images": {
                    "image_url": null,
                    "small_image_url": null,
                    "medium_image_url": null,
                    "large_image_url": null,
                    "maximum_image_url": null
                }
            },
            "approved": true,
            "titles": [
                {
                    "type": "Default",
                    "title": "Meng Li Ren"
                },
                {
                    "type": "Japanese",
                    "title": "\u5922\u88e1\u4eba"
                },
                {
                    "type": "English",
                    "title": "The Dreaming Girl"
                }
            ],
            "title": "Meng Li Ren",
            "title_english": "The Dreaming Girl",
            "title_japanese": "\u5922\u88e1\u4eba",
            "title_synonyms": [],
            "type": "TV",
            "source": "Unknown",
            "episodes": 26,
            "status": "Finished Airing",
            "airing": false,
            "aired": {
                "from": "2005-12-12T00:00:00+00:00",
                "to": "2006-01-06T00:00:00+00:00",
                "prop": {
                    "from": {
                        "day": 12,
                        "month": 12,
                        "year": 2005
                    },
                    "to": {
                        "day": 6,
                        "month": 1,
                        "year": 2006
                    }
                },
                "string": "Dec 12, 2005 to Jan 6, 2006"
            },
            "duration": "22 min per ep",
            "rating": "G - All Ages",
            "score": null,
            "scored_by": null,
            "rank": 18660,
            "popularity": 19376,
            "members": 440,
            "favorites": 1,
            "synopsis": null,
            "background": "",
            "season": "winter",
            "year": 2006,
            "broadcast": {
                "day": null,
                "time": null,
                "timezone": null,
                "string": "Unknown"
            },
            "producers": [],
            "licensors": [],
            "studios": [],
            "genres": [
                {
                    "mal_id": 8,
                    "type": "anime",
                    "name": "Drama",
                    "url": "https://myanimelist.net/anime/genre/8/Drama"
                }
            ],
            "explicit_genres": [],
            "themes": [],
            "demographics": []
        }
    ]
}